evosentinel/__init__.py
evosentinel/api.py
evosentinel/errors.py
evosentinel/core/__init__.py
evosentinel/core/decision_engine.py
evosentinel/core/risk_engine.py
evosentinel/core/signals.py
evosentinel/execution/__init__.py
evosentinel/execution/guard.py
evosentinel/execution/retry.py
evosentinel/hooks/__init__.py
evosentinel/hooks/lifecycle.py
evosentinel/modeling/__init__.py
evosentinel/modeling/baseline.py
evosentinel/modeling/decay.py
evosentinel/state/__init__.py
evosentinel/state/quarantine.py
evosentinel/state/state_machine.py
evosentinel-0.1.0.dist-info/licenses/LICENSE
evosentinel-0.1.0.dist-info/METADATA
evosentinel-0.1.0.dist-info/WHEEL
evosentinel-0.1.0.dist-info/top_level.txt
evosentinel-0.1.0.dist-info/RECORD
