Metadata-Version: 2.4
Name: evosentinel
Version: 0.1.0
Summary: Advanced Python Runtime Guard & Self-Healing Engine
Author-email: Daksha Dubey <your.email@example.com>
License: MIT
Project-URL: Homepage, https://github.com/dakshdubey/evoSentinel
Project-URL: Documentation, https://github.com/dakshdubey/evoSentinel#readme
Project-URL: Repository, https://github.com/dakshdubey/evoSentinel
Project-URL: Issues, https://github.com/dakshdubey/evoSentinel/issues
Keywords: reliability,fault-tolerance,circuit-breaker,self-healing,runtime-guard,sre,resilience
Classifier: Development Status :: 4 - Beta
Classifier: Intended Audience :: Developers
Classifier: License :: OSI Approved :: MIT License
Classifier: Programming Language :: Python :: 3
Classifier: Programming Language :: Python :: 3.8
Classifier: Programming Language :: Python :: 3.9
Classifier: Programming Language :: Python :: 3.10
Classifier: Programming Language :: Python :: 3.11
Classifier: Programming Language :: Python :: 3.12
Classifier: Topic :: Software Development :: Libraries :: Python Modules
Classifier: Topic :: System :: Monitoring
Requires-Python: >=3.8
License-File: LICENSE
Dynamic: license-file
